Metadata-Version: 2.4
Name: llama-index-readers-bilibili
Version: 0.4.1
Summary: llama-index readers bilibili integration
Author-email: Your Name <you@example.com>
Maintainer: alexzhangji
License-Expression: MIT
License-File: LICENSE
Requires-Python: <4.0,>=3.9
Requires-Dist: llama-index-core<0.15,>=0.13.0
